obsidian/__init__.py
obsidian/chat.py
obsidian/cli.py
obsidian/config.py
obsidian/core.py
obsidian/extract.py
obsidian/import_doc.py
obsidian/ingest.py
obsidian/server.py
obsidian/utils.py
obsidian_vault_rag-0.1.0.dist-info/METADATA
obsidian_vault_rag-0.1.0.dist-info/WHEEL
obsidian_vault_rag-0.1.0.dist-info/entry_points.txt
obsidian_vault_rag-0.1.0.dist-info/licenses/LICENSE
obsidian_vault_rag-0.1.0.dist-info/RECORD
