Metadata-Version: 2.4
Name: obsidian-vault-rag
Version: 0.1.0
Summary: Obsidian RAG CLI - Ingest and Chat with your notes
Project-URL: Homepage, https://github.com/sfilges/obsidian
Project-URL: Repository, https://github.com/sfilges/obsidian
Project-URL: Issues, https://github.com/sfilges/obsidian/issues
Project-URL: Changelog, https://github.com/sfilges/obsidian/blob/master/CHANGELOG.md
Project-URL: Documentation, https://github.com/sfilges/obsidian/blob/master/docs
Author-email: Stefan Filges <stefan.filges@pm.me>
License: MIT License
License-File: LICENSE
Keywords: ai,mcp,obsidian,rag,vector-database
Classifier: Development Status :: 4 - Beta
Classifier: Intended Audience :: Developers
Classifier: License :: OSI Approved :: MIT License
Classifier: Programming Language :: Python :: 3.10
Classifier: Programming Language :: Python :: 3.11
Classifier: Programming Language :: Python :: 3.12
Requires-Python: >=3.10
Requires-Dist: docling==2.67.0
Requires-Dist: einops
Requires-Dist: httpx>=0.27.0
Requires-Dist: lancedb==0.26.1
Requires-Dist: langchain-docling==2.0.0
Requires-Dist: langchain-text-splitters==1.1.0
Requires-Dist: mcp==1.25.0
Requires-Dist: pydantic==2.12.5
Requires-Dist: pyyaml==6.0.3
Requires-Dist: rich==13.7.0
Requires-Dist: ruff>=0.14.11
Requires-Dist: sentence-transformers==5.2.0
Requires-Dist: tenacity>=8.2.0
Requires-Dist: tqdm==4.67.1
Requires-Dist: typer>=0.15.0
Provides-Extra: dev
Requires-Dist: bandit[toml]>=1.8.0; extra == 'dev'
Requires-Dist: pre-commit>=4.0.0; extra == 'dev'
Requires-Dist: ruff>=0.14.11; extra == 'dev'
Provides-Extra: test
Requires-Dist: pytest>=9.0.2; extra == 'test'
